setup.py
ida2r2/__init__.py
ida2r2/common.py
ida2r2/ida_bytes.py
ida2r2/ida_funcs.py
ida2r2/ida_idaapi.py
ida2r2/ida_nalt.py
ida2r2/ida_name.py
ida2r2/ida_segment.py
ida2r2/ida_ua.py
ida2r2/idaapi.py
ida2r2/idautils.py
ida2r2/idc.py
ida2r2/r2.py
ida2r2.egg-info/PKG-INFO
ida2r2.egg-info/SOURCES.txt
ida2r2.egg-info/dependency_links.txt
ida2r2.egg-info/requires.txt
ida2r2.egg-info/top_level.txt