Metadata-Version: 2.1
Name: ida2r2
Version: 0.1.0
Summary: IDA API adaptation layer to r2
Home-page: https://github.com/FernandoDoming/ida2r2
Author: Fernando Domínguez
Author-email: fernando.dom.del@gmail.com
License: GNU GPL v3
Classifier: Programming Language :: Python :: 3.5
Classifier: Programming Language :: Python :: 3.6
Classifier: Programming Language :: Python :: 3.7
Classifier: Programming Language :: Python :: 3.8
Classifier: Programming Language :: Python :: 3.9
Classifier: Programming Language :: Python :: 3.10
